zencoder
