Metadata-Version: 1.0
Name: zencoder
Version: 0.6.5
Summary: Integration library for Zencoder
Home-page: http://github.com/schworer/zencoder-py
Author: Alex Schworer
Author-email: alex.schworer@gmail.com
License: MIT License
Platform: any
Classifier: Development Status :: 4 - Beta
Classifier: Intended Audience :: Developers
Classifier: License :: OSI Approved :: MIT License
Classifier: Operating System :: OS Independent
Classifier: Programming Language :: Python
Classifier: Programming Language :: Python :: 2.6
Classifier: Programming Language :: Python :: 2.7
Classifier: Topic :: Software Development :: Libraries :: Python Modules
